README
setup.py
tbucket.py
tbucket.egg-info/PKG-INFO
tbucket.egg-info/SOURCES.txt
tbucket.egg-info/dependency_links.txt
tbucket.egg-info/top_level.txt