Metadata-Version: 1.1
Name: tbucket
Version: 1.1.0
Summary: A sqlite-backed token bucket rate limiter implementation.
Home-page: http://github.com/AllSeeingEyeTolledEweSew/tbucket
Author: AllSeeingEyeTolledEweSew
Author-email: allseeingeyetolledewesew@protonmail.com
License: Unlicense
Platform: UNKNOWN
Classifier: Development Status :: 5 - Production/Stable
Classifier: Intended Audience :: Developers
Classifier: License :: Public Domain
Classifier: Programming Language :: Python
Classifier: Topic :: Software Development :: Libraries :: Python Modules
Classifier: Topic :: System :: Networking
Classifier: Topic :: Database
Classifier: Operating System :: OS Independent
Classifier: License :: Public Domain
